faissknn/__init__.py
faissknn/knn.py
faissknn-0.0.1.dist-info/LICENSE
faissknn-0.0.1.dist-info/METADATA
faissknn-0.0.1.dist-info/WHEEL
faissknn-0.0.1.dist-info/top_level.txt
faissknn-0.0.1.dist-info/RECORD
