Metadata-Version: 2.1
Name: faissknn
Version: 0.0.1
Summary: Faiss implementation of multiclass and multilabel K-Nearest Neighbors Classifiers
Home-page: https://github.com/isaaccorley/faissknn
Author: Isaac Corley
Author-email: isaac.corley@my.utsa.edu
Keywords: pytorch,machine learning,deep learning
Classifier: Development Status :: 3 - Alpha
Classifier: Intended Audience :: Science/Research
Classifier: Programming Language :: Python :: 3
Classifier: Programming Language :: Python :: 3.9
Classifier: Programming Language :: Python :: 3.10
Classifier: License :: OSI Approved :: MIT License
Classifier: Operating System :: OS Independent
Classifier: Topic :: Scientific/Engineering :: Artificial Intelligence
Requires-Python: <4,>=3.9
License-File: LICENSE
Requires-Dist: numpy
Provides-Extra: dev
Requires-Dist: black ; extra == 'dev'
Requires-Dist: isort[colors] ; extra == 'dev'
Requires-Dist: flake8 ; extra == 'dev'
Requires-Dist: pydocstyle ; extra == 'dev'
Requires-Dist: pytest ; extra == 'dev'
Requires-Dist: mypy ; extra == 'dev'
Requires-Dist: scikit-learn ; extra == 'dev'
